pyfairdatatools/__init__.py
pyfairdatatools/__main__.py
pyfairdatatools/assets/datatype_dictionary.yaml
pyfairdatatools/assets/languages.json
pyfairdatatools/assets/licenses.json
pyfairdatatools/cfpir.py
pyfairdatatools/cfpir_converter.py
pyfairdatatools/cfpir_metadata_extract.py
pyfairdatatools/classifying_rules.py
pyfairdatatools/cli.py
pyfairdatatools/generate.py
pyfairdatatools/gui.py
pyfairdatatools/identifier.py
pyfairdatatools/schemas/dataset_description.schema.json
pyfairdatatools/schemas/datatype_dictionary.schema.json
pyfairdatatools/schemas/folder_structure.schema.json
pyfairdatatools/schemas/participants.schema.json
pyfairdatatools/schemas/readme.schema.json
pyfairdatatools/schemas/study_description.schema.json
pyfairdatatools/standards.py
pyfairdatatools/templates/high-level-dataset-structure/CHANGELOG.md
pyfairdatatools/templates/high-level-dataset-structure/LICENSE.txt
pyfairdatatools/templates/high-level-dataset-structure/README.md
pyfairdatatools/templates/high-level-dataset-structure/activity_monitor/README.md
pyfairdatatools/templates/high-level-dataset-structure/best_corrected_visual_acuity/README.md
pyfairdatatools/templates/high-level-dataset-structure/dataset_description.json
pyfairdatatools/templates/high-level-dataset-structure/participants.json
pyfairdatatools/templates/high-level-dataset-structure/participants.tsv
pyfairdatatools/templates/readme.mdtxt.template
pyfairdatatools/tests/__init__.py
pyfairdatatools/tests/conftest.py
pyfairdatatools/utils.py
pyfairdatatools/validate.py
pyfairdatatools-1.0.3.dist-info/METADATA
pyfairdatatools-1.0.3.dist-info/WHEEL
pyfairdatatools-1.0.3.dist-info/entry_points.txt
pyfairdatatools-1.0.3.dist-info/licenses/LICENSE.md
pyfairdatatools-1.0.3.dist-info/RECORD
