Metadata-Version: 2.4
Name: pyfairdatatools
Version: 1.0.3
Summary: Tools for AI-READI
License: MIT
License-File: LICENSE.md
Author: FAIR Data Innovations Hub
Author-email: contact@fairdataihub.org
Requires-Python: >=3.8,<4.0
Classifier: Development Status :: 1 - Planning
Classifier: Intended Audience :: Developers
Classifier: License :: OSI Approved
Classifier: License :: OSI Approved :: MIT License
Classifier: Natural Language :: English
Classifier: Operating System :: OS Independent
Classifier: Programming Language :: Python
Classifier: Programming Language :: Python :: 3
Classifier: Programming Language :: Python :: 3.8
Classifier: Programming Language :: Python :: 3.9
Classifier: Programming Language :: Python :: 3.10
Classifier: Programming Language :: Python :: 3.11
Classifier: Programming Language :: Python :: 3.12
Classifier: Programming Language :: Python :: 3.13
Classifier: Programming Language :: Python :: 3.14
Requires-Dist: art (>=6.0,<7.0)
Requires-Dist: click
Requires-Dist: dicttoxml (>=1.7.16,<2.0.0)
Requires-Dist: jsonschema (>=4.17.3,<5.0.0)
Requires-Dist: minilog
Requires-Dist: pymdown-extensions (>=10.0.1,<11.0.0)
Requires-Dist: pyyaml (>=6.0.1,<7.0.0)
Requires-Dist: types-pyyaml (>=6.0.12.12,<7.0.0.0)
Requires-Dist: types-requests (>=2.30.0.0,<3.0.0.0)
Requires-Dist: urllib3 (<2.0)
Requires-Dist: validators (>=0.20.0,<0.21.0)
Project-URL: Documentation, https://pyfairdatatools.readthedocs.io
Project-URL: Homepage, https://pypi.org/project/pyfairdatatools
Project-URL: Repository, https://github.com/AI-READI/pyfairdatatools
